truffleHog/__init__.py
truffleHog/truffleHog.py
truffleHog-2.2.0.dist-info/LICENSE
truffleHog-2.2.0.dist-info/METADATA
truffleHog-2.2.0.dist-info/WHEEL
truffleHog-2.2.0.dist-info/entry_points.txt
truffleHog-2.2.0.dist-info/top_level.txt
truffleHog-2.2.0.dist-info/RECORD
