Metadata-Version: 2.1
Name: truffleHog
Version: 2.2.0
Summary: Searches through git repositories for high entropy strings, digging deep into commit history.
Home-page: https://github.com/dxa4481/truffleHog
Author: Dylan Ayrey
Author-email: dxa4481@rit.edu
License: GNU
Platform: UNKNOWN
Requires-Dist: GitPython (==3.0.6)
Requires-Dist: truffleHogRegexes (==0.0.7)
